usac_velodata/__init__.py
usac_velodata/__main__.py
usac_velodata/cli.py
usac_velodata/client.py
usac_velodata/exceptions.py
usac_velodata/models.py
usac_velodata/parser.py
usac_velodata/py.typed
usac_velodata/serializers.py
usac_velodata/utils.py
usac_velodata-2025.4.0.dist-info/METADATA
usac_velodata-2025.4.0.dist-info/WHEEL
usac_velodata-2025.4.0.dist-info/licenses/LICENSE
usac_velodata-2025.4.0.dist-info/RECORD
