Metadata-Version: 2.4
Name: usac-velodata
Version: 2025.4.0
Summary: Get events, and results from USAC
Author-email: Vincent Davis <vincent@heteroskedastic.net>
License-File: LICENSE
Requires-Python: >=3.13
Requires-Dist: beautifulsoup4>=4.13.3
Requires-Dist: httpx>=0.28.1
Requires-Dist: lxml>=5.3.1
Requires-Dist: pydantic>=2.11.1
Requires-Dist: python-dateutil>=2.9.0.post0
Requires-Dist: requests>=2.32.3
